lbrlabs_pulumi_iosxe
