Metadata-Version: 2.1
Name: lbrlabs-pulumi-iosxe
Version: 0.0.1
Summary: A Pulumi package for creating and managing Cisco IOS XE Devices.
Home-page: https://www.pulumi.com
License: Apache-2.0
Project-URL: Repository, https://github.com/lbrlabs/pulumi-iosxe
Keywords: pulumi iosxe category/utility
Platform: UNKNOWN
Requires-Python: >=3.7
